_xdelta3.cpython-36m-x86_64-linux-gnu.so
xdelta3/__init__.py
xdelta3/_xdelta3.c
xdelta3/main.py
xdelta3/version.py
xdelta3/lib/xdelta3-blkcache.h
xdelta3/lib/xdelta3-cfgs.h
xdelta3/lib/xdelta3-decode.h
xdelta3/lib/xdelta3-djw.h
xdelta3/lib/xdelta3-fgk.h
xdelta3/lib/xdelta3-hash.h
xdelta3/lib/xdelta3-internal.h
xdelta3/lib/xdelta3-list.h
xdelta3/lib/xdelta3-lzma.h
xdelta3/lib/xdelta3-main.h
xdelta3/lib/xdelta3-merge.h
xdelta3/lib/xdelta3-second.h
xdelta3/lib/xdelta3.c
xdelta3/lib/xdelta3.h
xdelta3-0.0.5.dist-info/DESCRIPTION.rst
xdelta3-0.0.5.dist-info/METADATA
xdelta3-0.0.5.dist-info/RECORD
xdelta3-0.0.5.dist-info/WHEEL
xdelta3-0.0.5.dist-info/metadata.json
xdelta3-0.0.5.dist-info/top_level.txt
xdelta3-0.0.5.dist-info/zip-safe
